odoo9_addon_stock_account_change_product_valuation-9.0.1.0.0.99.dev4-py3.8-nspkg.pth
odoo_addons/stock_account_change_product_valuation/README.rst
odoo_addons/stock_account_change_product_valuation/__init__.py
odoo_addons/stock_account_change_product_valuation/__openerp__.py
odoo_addons/stock_account_change_product_valuation/i18n/ca.po
odoo_addons/stock_account_change_product_valuation/i18n/de.po
odoo_addons/stock_account_change_product_valuation/i18n/es.po
odoo_addons/stock_account_change_product_valuation/i18n/es_MX.po
odoo_addons/stock_account_change_product_valuation/i18n/fi.po
odoo_addons/stock_account_change_product_valuation/i18n/fr.po
odoo_addons/stock_account_change_product_valuation/i18n/fr_CH.po
odoo_addons/stock_account_change_product_valuation/i18n/hr.po
odoo_addons/stock_account_change_product_valuation/i18n/hr_HR.po
odoo_addons/stock_account_change_product_valuation/i18n/it.po
odoo_addons/stock_account_change_product_valuation/i18n/pt_BR.po
odoo_addons/stock_account_change_product_valuation/i18n/ro.po
odoo_addons/stock_account_change_product_valuation/i18n/sl.po
odoo_addons/stock_account_change_product_valuation/i18n/stock_account_change_product_valuation.pot
odoo_addons/stock_account_change_product_valuation/i18n/tr_TR.po
odoo_addons/stock_account_change_product_valuation/i18n/vi_VN.po
odoo_addons/stock_account_change_product_valuation/i18n/zh_CN.po
odoo_addons/stock_account_change_product_valuation/models/__init__.py
odoo_addons/stock_account_change_product_valuation/models/product.py
odoo_addons/stock_account_change_product_valuation/models/product_category.py
odoo_addons/stock_account_change_product_valuation/static/description/icon.png
odoo_addons/stock_account_change_product_valuation/tests/__init__.py
odoo_addons/stock_account_change_product_valuation/tests/test_stock_account_product_change_product_type.py
odoo9_addon_stock_account_change_product_valuation-9.0.1.0.0.99.dev4.dist-info/METADATA
odoo9_addon_stock_account_change_product_valuation-9.0.1.0.0.99.dev4.dist-info/WHEEL
odoo9_addon_stock_account_change_product_valuation-9.0.1.0.0.99.dev4.dist-info/namespace_packages.txt
odoo9_addon_stock_account_change_product_valuation-9.0.1.0.0.99.dev4.dist-info/top_level.txt
odoo9_addon_stock_account_change_product_valuation-9.0.1.0.0.99.dev4.dist-info/RECORD
